pynamedotcom/__init__.py
pynamedotcom/__meta__.py
pynamedotcom/api.py
pynamedotcom/cli.py
pynamedotcom/contact.py
pynamedotcom/decorators.py
pynamedotcom/domain.py
pynamedotcom/exceptions.py
pynamedotcom/search.py
pynamedotcom-0.1.1.dist-info/METADATA
pynamedotcom-0.1.1.dist-info/RECORD
pynamedotcom-0.1.1.dist-info/WHEEL
pynamedotcom-0.1.1.dist-info/entry_points.txt
pynamedotcom-0.1.1.dist-info/top_level.txt
