Metadata-Version: 2.1
Name: pynamedotcom
Version: 0.1.1
Summary: A python library to interact with the name.com api.
Home-page: https://github.com/benmaddison/pynamedotcom
Author: Ben Maddison
Author-email: benm@workonline.co.za
License: MIT
Download-URL: https://github.com/benmaddison/pynamedotcom/0.1.1
Platform: UNKNOWN
Classifier: Development Status :: 4 - Beta
Classifier: Intended Audience :: Developers
Classifier: License :: OSI Approved :: MIT License
Classifier: Topic :: Software Development :: Libraries :: Python Modules
Classifier: Topic :: Internet
Requires-Dist: requests (<3.0,>=2.18.1)
Requires-Dist: click (<7.0,>=6.7)
